{
  "id": "33bdc76a-5474-4ebb-84ab-11a50ddd498e",
  "title": "Insulin",
  "body": "<h2>Insulin</h2><p><br></p><p>This summary contains important information about insulin. You should read this information and review it each time the prescription is filled. This sheet is provided as a summary and does not take the place of instructions from your veterinarian. Talk to your veterinarian if you do not understand any of this information or if you want to know more about insulin.</p><p><br></p><p>Insulin is an injectable hormone used to help control blood glucose (sugar) levels in pets with diabetes mellitus. It is administered as an injection, and it is very important to use the appropriately sized syringe (use U40 syringes to administer U40 insulin; use U100 syringes to administer U100 insulin).</p><p><br></p><p>YOUR PET SHOULD NOT BE GIVEN INSULIN IF HE/SHE HAS A KNOWN SENSITIVITY / ALLERGY TO INGREDIENTS IN THIS MEDICATION OR ANY RELATED COMPOUNDS.</p><p><br></p><p>HOW AND WHEN DO I GIVE THE MEDICINE TO MY PET?</p><p><br></p><ul><li>Always follow the doctor’s directions. Give the medicine as directed. Use it only as prescribed. See the medicine label for specific instructions.</li><li>Store insulin in the refrigerator in a consistent place (it is typically recommended to use a shelf rather than the door), unless otherwise directed. Follow directions for mixing prior to injection.</li></ul><p><br></p><p>WHAT SIDE EFFECTS MAY OCCUR?</p><p><br></p><p>Side effects are primarily related to inadvertent effects on blood glucose levels: excessive thirst and urination, increased appetite, and weight loss may be seen with increased blood glucose levels. Weakness, lethargy, collapse, and depressed neurologic state may be seen with low blood glucose levels.</p><p><br></p><p>WHEN SHOULD I CALL MY VETERINARIAN?</p><p><br></p><p>If your pet does not eat or drink at any time during the administration of this drug, please call your veterinarian. Call before stopping the medicine if any side effects occur or if the symptoms persist. Schedule follow-up visits as directed by your veterinarian. Your pet may require blood work and/or other diagnostic tests to check his or her response to the plan of care.</p><p><br></p><p>WARNINGS:</p><p><br></p><p>As with any product, consult your veterinarian before using this product on debilitated, aged, pregnant or nursing pets. If your pet is on any other medication, consult your veterinarian before using this or any other product. Tell your veterinarian about any medications or supplements you are giving, or plan to give your pet. Tell your veterinarian if your pet is pregnant, nursing, or if you plan to breed your pet.</p><p><br></p><p>PLEASE NOTE:</p><p><br></p><p>Call for a refill (if needed) 4-5 days before the last dose. Keep this and all medications out of the reach of children and other pets. Contact your physician immediately with any concerns of human exposure/ingestion.</p><p><br></p><p>References: Plumb’s Veterinary Drug Handbook, 8th edition</p><p><br></p><p>U.S. National Library of Medicine, National Institutes of Health</p>",
  "category": "Client_Instructions_Medical",
  "active": true,
  "animalClassId": "",
  "createdAt": "2026-01-13T09:11:46.489Z",
  "updatedAt": "2026-01-13T09:11:46.489Z"
}